windbot_pylib/__init__.py
windbot_pylib/db/__init__.py
windbot_pylib/db/models.py
windbot_pylib/db/utils.py
windbot_pylib/utils.py
windbot_pylib-0.2.6.dist-info/METADATA
windbot_pylib-0.2.6.dist-info/WHEEL
windbot_pylib-0.2.6.dist-info/RECORD
