Metadata-Version: 2.1
Name: windbot-pylib
Version: 0.2.6
Summary: 
Author: Dillan Hildebrand
Author-email: dillan.hildebrand@protonmail.com
Requires-Python: >=3.11,<4.0
Classifier: Programming Language :: Python :: 3
Classifier: Programming Language :: Python :: 3.11
Classifier: Programming Language :: Python :: 3.12
Requires-Dist: geoalchemy2 (>=0.16.0,<0.17.0)
Requires-Dist: sqlalchemy (>=2.0.36,<3.0.0)
